geo_colormaps/__init__.py
geo_colormaps/colormap.py
geo_colormaps/colormap_list.md
geo_colormaps/custom_errors.py
geo_colormaps/loader.py
geo_colormaps/colormap_defs/cma_colormaps/README.md
geo_colormaps/colormap_defs/cma_colormaps/alarm_level.csv
geo_colormaps/colormap_defs/cma_colormaps/draught_level.csv
geo_colormaps/colormap_defs/cma_colormaps/dtemp.csv
geo_colormaps/colormap_defs/cma_colormaps/flood_level.csv
geo_colormaps/colormap_defs/cma_colormaps/fog.csv
geo_colormaps/colormap_defs/cma_colormaps/pre_ano.csv
geo_colormaps/colormap_defs/cma_colormaps/pre_level.csv
geo_colormaps/colormap_defs/cma_colormaps/pre_total.csv
geo_colormaps/colormap_defs/cma_colormaps/rain_1h.csv
geo_colormaps/colormap_defs/cma_colormaps/rain_3h.csv
geo_colormaps/colormap_defs/cma_colormaps/rh.csv
geo_colormaps/colormap_defs/cma_colormaps/rh850.csv
geo_colormaps/colormap_defs/cma_colormaps/sandstorm_level.csv
geo_colormaps/colormap_defs/cma_colormaps/slp.csv
geo_colormaps/colormap_defs/cma_colormaps/slp_reversed.csv
geo_colormaps/colormap_defs/cma_colormaps/snow_depth.csv
geo_colormaps/colormap_defs/cma_colormaps/snow_level.csv
geo_colormaps/colormap_defs/cma_colormaps/sst.csv
geo_colormaps/colormap_defs/cma_colormaps/sst_conti.csv
geo_colormaps/colormap_defs/cma_colormaps/temp.csv
geo_colormaps/colormap_defs/cma_colormaps/temp_ano.csv
geo_colormaps/colormap_defs/cma_colormaps/temp_rt.csv
geo_colormaps/colormap_defs/cma_colormaps/vis.csv
geo_colormaps/colormap_defs/cma_colormaps/wind_level.csv
geo_colormaps/colormap_defs/cma_colormaps/ws10.csv
geo_colormaps/colormap_defs/cma_colormaps/ws10_typhoon.csv
geo_colormaps/colormap_defs/other_colormaps/README.md
geo_colormaps/colormap_defs/other_colormaps/cth_conti.csv
geo_colormaps/colormap_defs/other_colormaps/ctt_conti.csv
geo_colormaps/colormap_defs/other_colormaps/rain_12h.csv
geo_colormaps/colormap_defs/other_colormaps/rain_1h.csv
geo_colormaps/colormap_defs/other_colormaps/rain_24h.csv
geo_colormaps-0.3.0.dist-info/licenses/LICENSE
geo_colormaps-0.3.0.dist-info/METADATA
geo_colormaps-0.3.0.dist-info/WHEEL
geo_colormaps-0.3.0.dist-info/top_level.txt
geo_colormaps-0.3.0.dist-info/RECORD
