Metadata-Version: 2.4
Name: geo_colormaps
Version: 0.3.0
Summary: geo_colormap is a collection of standard weather/ocean colormaps, for creating plots using `matplotlib`. It allows easy additions of custom colormaps using csv tables.
Home-page: https://github.com/Xunius/geo_colormaps
Author: Guangzhi XU
Author-email: xugzhi1987@gmail.com
License: GPL-3.0-or-later
Classifier: Development Status :: 3 - Alpha
Classifier: Environment :: Console
Classifier: Intended Audience :: Science/Research
Classifier: License :: OSI Approved :: GNU General Public License v3 (GPLv3)
Classifier: Natural Language :: English
Classifier: Operating System :: POSIX :: Linux
Classifier: Operating System :: MacOS
Classifier: Operating System :: Microsoft :: Windows
Classifier: Programming Language :: Python :: 3
Classifier: Topic :: Scientific/Engineering :: Atmospheric Science
Requires-Python: >=3.5
License-File: LICENSE
Requires-Dist: numpy
Requires-Dist: matplotlib
Dynamic: author
Dynamic: author-email
Dynamic: classifier
Dynamic: home-page
Dynamic: license
Dynamic: license-file
Dynamic: requires-dist
Dynamic: requires-python
Dynamic: summary
